deeprm/__init__.py
deeprm/__main__.py
deeprm/cli.py
deeprm/inference/__init__.py
deeprm/inference/cli.py
deeprm/inference/deeprm_preprocess
deeprm/inference/inference.py
deeprm/inference/inference_dataloader.py
deeprm/inference/inference_preprocess.py
deeprm/inference/inference_preprocess_python.py
deeprm/inference/pileup_deeprm.py
deeprm/inference/pileup_genomic.py
deeprm/model/__init__.py
deeprm/model/deeprm_model.py
deeprm/qc/__init__.py
deeprm/qc/cli.py
deeprm/qc/inspect_alignment.py
deeprm/qc/inspect_block.py
deeprm/qc/inspect_run.py
deeprm/train/__init__.py
deeprm/train/cli.py
deeprm/train/extract_block.py
deeprm/train/train.py
deeprm/train/train_compile.py
deeprm/train/train_dataloader.py
deeprm/train/train_preprocess.py
deeprm/train/config/dag_config.json
deeprm/utils/__init__.py
deeprm/utils/activations.py
deeprm/utils/check_deps.py
deeprm/utils/check_installation.py
deeprm/utils/logging.py
deeprm/utils/memory.py
deeprm/utils/utils.py
deeprm/weight/deeprm_weights.pt
deeprm-1.0.7.dist-info/licenses/LICENSE.md
deeprm-1.0.7.dist-info/METADATA
deeprm-1.0.7.dist-info/WHEEL
deeprm-1.0.7.dist-info/entry_points.txt
deeprm-1.0.7.dist-info/top_level.txt
deeprm-1.0.7.dist-info/RECORD
