Metadata-Version: 2.4
Name: deeprm
Version: 1.0.7
Summary: DeepRM: Deep Learning for RNA Modification Detection using Nanopore Direct RNA Sequencing
Author: Laboratory of Computational Biology, Seoul National University
License: MIT
Project-URL: Homepage, https://github.com/vadanamu/deeprm
Project-URL: Documentation, https://deeprm.readthedocs.io/
Project-URL: Source, https://github.com/vadanamu/deeprm
Keywords: RNA,RNA modification,m6A,nanopore,bioinformatics,deep learning
Classifier: Development Status :: 4 - Beta
Classifier: Programming Language :: Python :: 3
Classifier: Programming Language :: Python :: 3 :: Only
Classifier: Programming Language :: Python :: 3.9
Classifier: Programming Language :: Python :: 3.10
Classifier: Programming Language :: Python :: 3.11
Classifier: Programming Language :: Python :: 3.12
Classifier: Operating System :: POSIX :: Linux
Classifier: Topic :: Scientific/Engineering :: Bio-Informatics
Classifier: Intended Audience :: Science/Research
Requires-Python: >=3.9
License-File: LICENSE.md
Requires-Dist: colorama
Requires-Dist: tqdm
Requires-Dist: psutil
Requires-Dist: networkx>=3.1
Requires-Dist: numpy<3.0,>=1.24
Requires-Dist: pandas>=2.0
Requires-Dist: polyleven>=0.8
Requires-Dist: pod5>=0.3.2
Requires-Dist: pysam>=0.22.0
Requires-Dist: matplotlib>=3.7
Requires-Dist: seaborn>=0.12
Requires-Dist: tensorboard>=2.0
Provides-Extra: docs
Requires-Dist: sphinx<8,>=7; extra == "docs"
Requires-Dist: furo; extra == "docs"
Requires-Dist: myst-parser; extra == "docs"
Requires-Dist: sphinx-copybutton; extra == "docs"
Requires-Dist: sphinxcontrib-mermaid; extra == "docs"
Requires-Dist: sphinx-argparse; extra == "docs"
Requires-Dist: sphinx-autosummary-accessors; extra == "docs"
Requires-Dist: sphinx_design; extra == "docs"
Provides-Extra: test
Requires-Dist: black>=23.7.0; extra == "test"
Requires-Dist: isort>=5.12.0; extra == "test"
Requires-Dist: ruff>=0.4.0; extra == "test"
Requires-Dist: pytest>=7.4.0; extra == "test"
Requires-Dist: pytest-cov>=4.1.0; extra == "test"
Requires-Dist: pytest-mock>=3.10.0; extra == "test"
Requires-Dist: pytest-xdist>=3.3.1; extra == "test"
Dynamic: license-file
